django_webmap_corpus-0.6.dist-info/DESCRIPTION.rst
django_webmap_corpus-0.6.dist-info/METADATA
django_webmap_corpus-0.6.dist-info/RECORD
django_webmap_corpus-0.6.dist-info/WHEEL
django_webmap_corpus-0.6.dist-info/metadata.json
django_webmap_corpus-0.6.dist-info/top_level.txt
webmap/__init__.py
webmap/admin.py
webmap/admin_image_widget.py
webmap/apps.py
webmap/models.py
webmap/rest.py
webmap/urls.py
webmap/utils.py
webmap/views.py
webmap/locale/cs_CZ/LC_MESSAGES/django.po
webmap/migrations/0001_initial.py
webmap/migrations/0002_layer_icon.py
webmap/migrations/0003_marker_order.py
webmap/migrations/0004_auto_20150112_0935.py
webmap/migrations/0005_auto_20150607_1533.py
webmap/migrations/0006_auto_20150607_1534.py
webmap/migrations/0007_auto_20150616_1606.py
webmap/migrations/0008_mappreset_status.py
webmap/migrations/0009_mappreset_desc.py
webmap/migrations/__init__.py
webmap/static/.empty
webmap/static/django_webmap_corpus/.empty
webmap/static/django_webmap_corpus/js/OpenLayers.js
webmap/static/django_webmap_corpus/js/img/blank.gif
webmap/static/django_webmap_corpus/js/img/close.gif
webmap/static/django_webmap_corpus/js/img/close.gif.png
webmap/static/django_webmap_corpus/js/img/close_18.png
webmap/static/django_webmap_corpus/js/img/cloud-popup-relative.png
webmap/static/django_webmap_corpus/js/img/drag-rectangle-off.png
webmap/static/django_webmap_corpus/js/img/drag-rectangle-on.png
webmap/static/django_webmap_corpus/js/img/east-mini.png
webmap/static/django_webmap_corpus/js/img/layer-switcher-maximize.png
webmap/static/django_webmap_corpus/js/img/layer-switcher-minimize.png
webmap/static/django_webmap_corpus/js/img/marker-blue.png
webmap/static/django_webmap_corpus/js/img/marker-gold.png
webmap/static/django_webmap_corpus/js/img/marker-green.png
webmap/static/django_webmap_corpus/js/img/marker.png
webmap/static/django_webmap_corpus/js/img/measuring-stick-off.png
webmap/static/django_webmap_corpus/js/img/measuring-stick-on.png
webmap/static/django_webmap_corpus/js/img/my-cloud-popup-relative2.png
webmap/static/django_webmap_corpus/js/img/my-cloud-popup-relative2.xcf
webmap/static/django_webmap_corpus/js/img/north-mini.png
webmap/static/django_webmap_corpus/js/img/panning-hand-off.png
