Metadata-Version: 2.0
Name: django-webmap-corpus
Version: 0.6
Summary: Corpus for making web map applications.
Requires-Dist: django
Requires-Dist: django-admin-sortable2
Requires-Dist: django-author (>=0.2)
Requires-Dist: django-colorful
Requires-Dist: django-constance[database]
Requires-Dist: django-filter
Requires-Dist: django-finegrained-permissions
Requires-Dist: django-import-export
Requires-Dist: djangorestframework
Requires-Dist: easy-thumbnails
Requires-Dist: gpxpy
Requires-Dist: pillow
Requires-Dist: psycopg2
Provides-Extra: dev
Requires-Dist: django-jasmine; extra == 'dev'
Requires-Dist: django-nose; extra == 'dev'
Requires-Dist: flake8; extra == 'dev'
